pytest_services/__init__.py
pytest_services/django_settings.py
pytest_services/folders.py
pytest_services/locks.py
pytest_services/log.py
pytest_services/memcached.py
pytest_services/mysql.py
pytest_services/plugin.py
pytest_services/process.py
pytest_services/service.py
pytest_services/xvfb.py
pytest_services-2.2.2.dist-info/licenses/AUTHORS.rst
pytest_services-2.2.2.dist-info/licenses/LICENSE.txt
pytest_services-2.2.2.dist-info/METADATA
pytest_services-2.2.2.dist-info/WHEEL
pytest_services-2.2.2.dist-info/entry_points.txt
pytest_services-2.2.2.dist-info/top_level.txt
pytest_services-2.2.2.dist-info/RECORD
