Metadata-Version: 2.4
Name: pytest-services
Version: 2.2.2
Summary: Services plugin for pytest testing framework
Home-page: https://github.com/pytest-dev/pytest-services
Author: Anatoly Bubenkov, Paylogic International and others
Author-email: bubenkoff@gmail.com
License: MIT
Classifier: Development Status :: 6 - Mature
Classifier: Intended Audience :: Developers
Classifier: Operating System :: POSIX
Classifier: Operating System :: Microsoft :: Windows
Classifier: Operating System :: MacOS :: MacOS X
Classifier: Topic :: Software Development :: Testing
Classifier: Topic :: Software Development :: Libraries
Classifier: Topic :: Utilities
Classifier: Programming Language :: Python :: 2
Classifier: Programming Language :: Python :: 3
Classifier: Programming Language :: Python :: 3.9
Classifier: Programming Language :: Python :: 3.10
Classifier: Programming Language :: Python :: 3.11
Classifier: Programming Language :: Python :: 3.12
Classifier: Programming Language :: Python :: 3.13
Classifier: Programming Language :: Python :: 3.14
Requires-Python: >=3.9
License-File: LICENSE.txt
License-File: AUTHORS.rst
Requires-Dist: requests
Requires-Dist: psutil
Requires-Dist: pytest
Requires-Dist: zc.lockfile>=2.0
Dynamic: author
Dynamic: author-email
Dynamic: classifier
Dynamic: description
Dynamic: description-content-type
Dynamic: home-page
Dynamic: license
Dynamic: license-file
Dynamic: requires-dist
Dynamic: requires-python
Dynamic: summary
